xmonitor/__init__.py
xmonitor/cmds/__init__.py
xmonitor/cmds/glances.py
xmonitor/cmds/logrotate.py
xmonitor/utils/__init__.py
xmonitor/utils/attribute.py
xmonitor/utils/glances.py
xmonitor/utils/logrotate.py
xmonitor-0.2.dist-info/LICENSE
xmonitor-0.2.dist-info/METADATA
xmonitor-0.2.dist-info/WHEEL
xmonitor-0.2.dist-info/entry_points.txt
xmonitor-0.2.dist-info/top_level.txt
xmonitor-0.2.dist-info/zip-safe
xmonitor-0.2.dist-info/RECORD
